{
  "question_answer_pairs": [
    {
      "question_text": "Die Steuerfahndung eines deutschen Finanzamts erhält am 15.09.2013 ein Ersuchen der Strafverfolgungsbehörde eines anderen EU-Mitgliedstaates um Übermittlung personenbezogener Daten zur Verhütung einer dort geplanten Steuerhinterziehung. Unter welchen gesetzlichen Voraussetzungen darf die Steuerfahndung diese personenbezogenen Daten an die ersuchende Behörde übermitteln?",
      "answer_text": "Am 15.09.2013 gilt die Fassung des § 117a AO, die seit dem 26.07.2012 in Kraft ist. Die mit der Steuerfahndung betrauten Dienststellen der Finanzbehörden dürfen personenbezogene Daten, die im Zusammenhang mit dem in § 208 AO bestimmten Aufgabenbereich stehen, zum Zweck der Verhütung von Straftaten an eine für die Verhütung und Verfolgung von Straftaten zuständige öffentliche Stelle eines EU-Mitgliedstaates übermitteln, wenn ein entsprechendes Ersuchen dieser Stelle vorliegt (§ 117a AO Abs. 1). Für die Übermittlung gelten die Vorschriften über die Datenübermittlung im innerstaatlichen Bereich entsprechend. Die Übermittlung ist nur zulässig, wenn das Ersuchen mindestens die in § 117a AO Abs. 2 Nr. 1–7 genannten Angaben enthält (Bezeichnung und Anschrift der ersuchenden Behörde, Bezeichnung der Straftat, Sachverhaltsbeschreibung, Zweck der Datenanforderung, Zusammenhang zwischen Zweck und betroffener Person, Identitätsangaben zur betroffenen Person, soweit bekannt, sowie Gründe für die Annahme, dass sachdienliche Informationen im Inland vorliegen). Zudem darf keiner der zwingenden Versagungsgründe des § 117a AO Abs. 5 vorliegen (insbesondere keine Beeinträchtigung wesentlicher Sicherheitsinteressen, kein Verstoß gegen die Grundsätze des Art. 6 EUV, keine Notwendigkeit von Zwangsmaßnahmen zur erstmaligen Beschaffung der Daten und keine Unverhältnismäßigkeit oder fehlende Erforderlichkeit der Übermittlung).",
      "legal_basis": [
        {
          "law": "AO",
          "citation": "§ 117a AO Abs. 1",
          "version_valid_from": "2012-07-26",
          "version_valid_to": null
        },
        {
          "law": "AO",
          "citation": "§ 117a AO Abs. 2",
          "version_valid_from": "2012-07-26",
          "version_valid_to": null
        },
        {
          "law": "AO",
          "citation": "§ 117a AO Abs. 2 Nr. 1",
          "version_valid_from": "2012-07-26",
          "version_valid_to": null
        },
        {
          "law": "AO",
          "citation": "§ 117a AO Abs. 2 Nr. 2",
          "version_valid_from": "2012-07-26",
          "version_valid_to": null
        },
        {
          "law": "AO",
          "citation": "§ 117a AO Abs. 2 Nr. 3",
          "version_valid_from": "2012-07-26",
          "version_valid_to": null
        },
        {
          "law": "AO",
          "citation": "§ 117a AO Abs. 2 Nr. 4",
          "version_valid_from": "2012-07-26",
          "version_valid_to": null
        },
        {
          "law": "AO",
          "citation": "§ 117a AO Abs. 2 Nr. 5",
          "version_valid_from": "2012-07-26",
          "version_valid_to": null
        },
        {
          "law": "AO",
          "citation": "§ 117a AO Abs. 2 Nr. 6",
          "version_valid_from": "2012-07-26",
          "version_valid_to": null
        },
        {
          "law": "AO",
          "citation": "§ 117a AO Abs. 2 Nr. 7",
          "version_valid_from": "2012-07-26",
          "version_valid_to": null
        },
        {
          "law": "AO",
          "citation": "§ 117a AO Abs. 5",
          "version_valid_from": "2012-07-26",
          "version_valid_to": null
        }
      ],
      "relevant_fact_date": "2013-09-15",
      "source_versions": [
        {
          "file": "§117a_AO_vorgaenger.json",
          "valid_from": null,
          "valid_to": "2012-07-26"
        },
        {
          "file": "§117a_AO_nachfolger.json",
          "valid_from": "2012-07-26",
          "valid_to": null
        }
      ]
    }
  ],
  "source_versions": [
    {
      "file": "data/AO/s117a/ao_s117a_until_2012-07-26.json",
      "valid_from": null,
      "valid_to": "2012-07-26"
    },
    {
      "file": "data/AO/s117a/ao_s117a_current.json",
      "valid_from": "2012-07-26",
      "valid_to": null
    }
  ],
  "legal_basis": [
    {
      "law": "AO",
      "citation": "§ 117a AO",
      "version_valid_from": "2012-07-26",
      "version_valid_to": null
    }
  ],
  "relevant_fact_date": "2012-07-26",
  "validation": {
    "status": "pass",
    "issues": []
  }
}